pautodock/__autogridmap2dx__.py
pautodock/__init__.py
pautodock/__main__.py
pautodock/__recover_output__.py
pautodock/adparallel.py
pautodock/fileutils.py
pautodock/mgltoolsinstall.py
pautodock/molop.py
pautodock/multimol2op.py
pautodock-1.0.1.dist-info/METADATA
pautodock-1.0.1.dist-info/WHEEL
pautodock-1.0.1.dist-info/entry_points.txt
pautodock-1.0.1.dist-info/RECORD
