Metadata-Version: 2.1
Name: pautodock
Version: 1.0.1
Summary: A simple tool to parallelize AutoDock JOBs
Home-page: https://github.com/gmrandazzo/PAutoDock
License: lglpv3
Author: Giuseppe Marco Randazzo
Author-email: gmrandazzo@gmail.com
Requires-Python: >=3.8,<4.0
Classifier: Development Status :: 3 - Alpha
Classifier: License :: OSI Approved :: GNU Lesser General Public License v3 (LGPLv3)
Classifier: License :: Other/Proprietary License
Classifier: Operating System :: MacOS :: MacOS X
Classifier: Operating System :: POSIX :: Linux
Classifier: Programming Language :: Python :: 3
Classifier: Programming Language :: Python :: 3.8
Classifier: Programming Language :: Python :: 3.9
Classifier: Programming Language :: Python :: 3.10
Classifier: Programming Language :: Python :: 3.11
Classifier: Programming Language :: Python :: 3.12
Classifier: Programming Language :: Python :: 3.13
Classifier: Topic :: Scientific/Engineering :: Bio-Informatics
Requires-Dist: requests (>=2.32.3,<3.0.0)
Project-URL: Repository, https://github.com/gmrandazzo/PAutoDock
